fuzzy_systems/__init__.py
fuzzy_systems/cli.py
fuzzy_systems/interface.py
fuzzy_systems/core/__init__.py
fuzzy_systems/core/defuzzification.py
fuzzy_systems/core/fuzzification.py
fuzzy_systems/core/membership.py
fuzzy_systems/core/operators.py
fuzzy_systems/dynamics/README.md
fuzzy_systems/dynamics/__init__.py
fuzzy_systems/dynamics/fuzzy_ode.py
fuzzy_systems/dynamics/pfuzzy.py
fuzzy_systems/inference/__init__.py
fuzzy_systems/inference/rules.py
fuzzy_systems/inference/systems.py
fuzzy_systems/learning/README.md
fuzzy_systems/learning/__init__.py
fuzzy_systems/learning/anfis.py
fuzzy_systems/learning/anfis_metaheuristic.py.old
fuzzy_systems/learning/mamdani_neuro_fuzzy.py.old
fuzzy_systems/learning/mamdani_optimization.py.old
fuzzy_systems/learning/mandani_learning.py
fuzzy_systems/learning/metaheuristics.py
fuzzy_systems/learning/wang_mendel.py
fuzzy_systems/streamlit_app/QUICKSTART.md
fuzzy_systems/streamlit_app/README.md
fuzzy_systems/streamlit_app/__init__.py
fuzzy_systems/streamlit_app/main.py
fuzzy_systems/streamlit_app/requirements.txt
fuzzy_systems/streamlit_app/.streamlit/config.toml
fuzzy_systems/streamlit_app/modules/__init__.py
fuzzy_systems/streamlit_app/modules/anfis_module.py
fuzzy_systems/streamlit_app/modules/dynamics_pfuzzy_continuous.py
fuzzy_systems/streamlit_app/modules/dynamics_pfuzzy_continuous_obsolete.py
fuzzy_systems/streamlit_app/modules/dynamics_pfuzzy_discrete.py
fuzzy_systems/streamlit_app/modules/fuzzy_ode_module.py
fuzzy_systems/streamlit_app/modules/home.py
fuzzy_systems/streamlit_app/modules/inference.py
fuzzy_systems/streamlit_app/modules/inference_engine.py
fuzzy_systems/streamlit_app/modules/inference_mamdani.py
fuzzy_systems/streamlit_app/modules/inference_sugeno.py
fuzzy_systems/streamlit_app/modules/learning.py
fuzzy_systems/streamlit_app/modules/wang_mendel_module.py
fuzzy_systems/streamlit_app/modules/anfis/__init__.py
fuzzy_systems/streamlit_app/modules/anfis/analysis_tab.py
pyfuzzy_toolbox-1.1.6.dist-info/licenses/LICENSE
pyfuzzy_toolbox-1.1.6.dist-info/METADATA
pyfuzzy_toolbox-1.1.6.dist-info/WHEEL
pyfuzzy_toolbox-1.1.6.dist-info/entry_points.txt
pyfuzzy_toolbox-1.1.6.dist-info/top_level.txt
pyfuzzy_toolbox-1.1.6.dist-info/RECORD
