Metadata-Version: 2.4
Name: pyfuzzy-toolbox
Version: 1.1.6
Summary: A comprehensive Python library for fuzzy systems: inference (Mamdani, Sugeno), learning (ANFIS, Wang-Mendel, MandaniLearning), and dynamics (p-fuzzy, fuzzy ODEs)
Home-page: https://github.com/1moi6/pyfuzzy-toolbox
Author: Moiseis Cecconello
Author-email: Moiseis Cecconello <moiseis@gmail.com>
Maintainer-email: Moiseis Cecconello <moiseis@gmail.com>
License: MIT
Project-URL: Homepage, https://github.com/1moi6/pyfuzzy-toolbox
Project-URL: Documentation, https://github.com/1moi6/pyfuzzy-toolbox#readme
Project-URL: Repository, https://github.com/1moi6/pyfuzzy-toolbox
Project-URL: Bug Tracker, https://github.com/1moi6/pyfuzzy-toolbox/issues
Project-URL: Changelog, https://github.com/1moi6/pyfuzzy-toolbox/blob/main/CHANGELOG.md
Keywords: fuzzy logic,p-fuzzy systems,fuzzy inference,mamdani,sugeno,anfis,wang-mendel,machine learning,fuzzy ode,p-fuzzy,artificial intelligence,control systems
Classifier: Development Status :: 4 - Beta
Classifier: Intended Audience :: Education
Classifier: Intended Audience :: Science/Research
Classifier: Intended Audience :: Developers
Classifier: Topic :: Scientific/Engineering :: Artificial Intelligence
Classifier: Topic :: Scientific/Engineering :: Mathematics
Classifier: Topic :: Software Development :: Libraries :: Python Modules
Classifier: License :: OSI Approved :: MIT License
Classifier: Programming Language :: Python :: 3
Classifier: Programming Language :: Python :: 3.8
Classifier: Programming Language :: Python :: 3.9
Classifier: Programming Language :: Python :: 3.10
Classifier: Programming Language :: Python :: 3.11
Classifier: Programming Language :: Python :: 3.12
Classifier: Operating System :: OS Independent
Requires-Python: >=3.8
License-File: LICENSE
Requires-Dist: numpy>=1.20.0
Requires-Dist: matplotlib>=3.3.0
Requires-Dist: scipy>=1.6.0
Requires-Dist: typer[all]>=0.9.0
Requires-Dist: rich>=13.0.0
Provides-Extra: ui
Requires-Dist: streamlit>=1.20.0; extra == "ui"
Requires-Dist: plotly>=5.0.0; extra == "ui"
Provides-Extra: ml
Requires-Dist: scikit-learn>=0.24; extra == "ml"
Requires-Dist: pandas>=1.2; extra == "ml"
Requires-Dist: joblib>=1.0; extra == "ml"
Provides-Extra: dev
Requires-Dist: pytest>=6.0; extra == "dev"
Requires-Dist: pytest-cov>=2.12; extra == "dev"
Requires-Dist: black>=21.0; extra == "dev"
Requires-Dist: flake8>=3.9; extra == "dev"
Requires-Dist: mypy>=0.910; extra == "dev"
Provides-Extra: docs
Requires-Dist: sphinx>=4.0; extra == "docs"
Requires-Dist: sphinx-rtd-theme>=0.5; extra == "docs"
Requires-Dist: nbsphinx>=0.8; extra == "docs"
Provides-Extra: all
Requires-Dist: streamlit>=1.20.0; extra == "all"
Requires-Dist: plotly>=5.0.0; extra == "all"
Requires-Dist: scikit-learn>=0.24; extra == "all"
Requires-Dist: pandas>=1.2; extra == "all"
Requires-Dist: joblib>=1.0; extra == "all"
Requires-Dist: pytest>=6.0; extra == "all"
Requires-Dist: pytest-cov>=2.12; extra == "all"
Requires-Dist: black>=21.0; extra == "all"
Requires-Dist: flake8>=3.9; extra == "all"
Requires-Dist: mypy>=0.910; extra == "all"
Dynamic: author
Dynamic: home-page
Dynamic: license-file
Dynamic: requires-python
